au_execute/__init__.py
au_execute/commands.py
au_execute/executor.py
au_execute-0.1.1.dist-info/METADATA
au_execute-0.1.1.dist-info/WHEEL
au_execute-0.1.1.dist-info/RECORD
