Metadata-Version: 2.3
Name: au_execute
Version: 0.1.1
Summary: Framework para pipelines de procesamiento de datos con Spark
License: MIT
Author: Faustino Lopez Ramos
Author-email: faustinolopezramos@gmail.com
Requires-Python: >=3.8,<4.0
Classifier: License :: OSI Approved :: MIT License
Classifier: Programming Language :: Python :: 3
Classifier: Programming Language :: Python :: 3.8
Classifier: Programming Language :: Python :: 3.9
Classifier: Programming Language :: Python :: 3.10
Classifier: Programming Language :: Python :: 3.11
Classifier: Programming Language :: Python :: 3.12
Classifier: Programming Language :: Python :: 3.13
Requires-Dist: loguru (>=0.7.0,<0.8.0)
Requires-Dist: pyyaml (>=6.0.1,<7.0.0)
